zzupy/__init__.py
zzupy/crypto.py
zzupy/exception.py
zzupy/models.py
zzupy/utils.py
zzupy/aio/__init__.py
zzupy/aio/app/__init__.py
zzupy/aio/app/auth.py
zzupy/aio/app/ecard.py
zzupy/aio/app/interfaces.py
zzupy/aio/app/supwisdom.py
zzupy/aio/web/__init__.py
zzupy/aio/web/network.py
zzupy/app/__init__.py
zzupy/app/auth.py
zzupy/app/ecard.py
zzupy/app/interfaces.py
zzupy/app/supwisdom.py
zzupy/web/__init__.py
zzupy/web/network.py
zzupy-6.0.2.dist-info/METADATA
zzupy-6.0.2.dist-info/WHEEL
zzupy-6.0.2.dist-info/licenses/LICENSE
zzupy-6.0.2.dist-info/RECORD
