Metadata-Version: 2.4
Name: zzupy
Version: 6.0.2
Summary: 豫见郑大的 Python API 封装 / An API wrapper for Zhengzhou University Mobile Campus written in Python.
Project-URL: Repository, https://github.com/Illustar0/ZZU.Py
Project-URL: Documentation, https://illustar0.github.io/ZZU.Py
Author-email: Illustar0 <me@illustar0.com>
License-Expression: MIT
License-File: LICENSE
Requires-Python: >=3.11
Requires-Dist: beautifulsoup4>=4.13.3
Requires-Dist: gmalg>=1.0.6
Requires-Dist: httpx>=0.28.1
Requires-Dist: ifaddr>=0.2.0
Requires-Dist: loguru>=0.7.3
Requires-Dist: pydantic>=2.11.7
Requires-Dist: pyjwt>=2.10.1
Requires-Dist: typing-extensions>=4.12.2
Provides-Extra: ci
Requires-Dist: ruff>=0.13.1; extra == 'ci'
Provides-Extra: docs
Requires-Dist: jieba>=0.42.1; extra == 'docs'
Requires-Dist: markdown-callouts>=0.4.0; extra == 'docs'
Requires-Dist: markdown-exec>=1.11.0; extra == 'docs'
Requires-Dist: mkdocs-git-revision-date-localized-plugin>=1.4.7; extra == 'docs'
Requires-Dist: mkdocs-include-markdown-plugin>=7.1.7; extra == 'docs'
Requires-Dist: mkdocs-llmstxt>=0.3.1; extra == 'docs'
Requires-Dist: mkdocs-material>=9.6.20; extra == 'docs'
Requires-Dist: mkdocs-minify-plugin>=0.8.0; extra == 'docs'
Requires-Dist: mkdocs-redirects>=1.2.2; extra == 'docs'
Requires-Dist: mkdocs-section-index>=0.3.10; extra == 'docs'
Requires-Dist: mkdocs>=1.6.1; extra == 'docs'
Requires-Dist: mkdocstrings>=0.30.0; extra == 'docs'
Requires-Dist: mkdocstrings[python]>=0.30.0; extra == 'docs'
